README.md
setup.cfg
setup.py
openapi_client/__init__.py
openapi_client/api_client.py
openapi_client/configuration.py
openapi_client/exceptions.py
openapi_client/rest.py
openapi_client/api/__init__.py
openapi_client/api/default_api.py
openapi_client/models/__init__.py
openapi_client/models/assessment_type.py
openapi_client/models/ats_type.py
openapi_client/models/configuration.py
openapi_client/models/error_response.py
openapi_client/models/list_orders_request.py
openapi_client/models/list_orders_response.py
openapi_client/models/mercury_assessment.py
openapi_client/models/mercury_assessment_order.py
openapi_client/models/mercury_candidate.py
openapi_client/models/mercury_development_report_content.py
openapi_client/models/mercury_factor_content.py
openapi_client/models/mercury_model_direction.py
openapi_client/models/mercury_order_factor_content.py
openapi_client/models/mercury_order_metadata.py
openapi_client/models/mercury_report.py
openapi_client/models/mercury_result.py
openapi_client/models/mercury_retrieve_factor_content_request.py
openapi_client/models/o_auth_request.py
openapi_client/models/o_auth_response.py
openapi_client/models/order_create_response.py
openapi_client/models/order_request.py
openapi_client/models/pontem_order_statuses.py
openapi_client/models/pontem_report_types.py
python_pymetrics_assessment_client.egg-info/PKG-INFO
python_pymetrics_assessment_client.egg-info/SOURCES.txt
python_pymetrics_assessment_client.egg-info/dependency_links.txt
python_pymetrics_assessment_client.egg-info/requires.txt
python_pymetrics_assessment_client.egg-info/top_level.txt
test/test_assessment_type.py
test/test_ats_type.py
test/test_configuration.py
test/test_default_api.py
test/test_error_response.py
test/test_list_orders_request.py
test/test_list_orders_response.py
test/test_mercury_assessment.py
test/test_mercury_assessment_order.py
test/test_mercury_candidate.py
test/test_mercury_development_report_content.py
test/test_mercury_factor_content.py
test/test_mercury_model_direction.py
test/test_mercury_order_factor_content.py
test/test_mercury_order_metadata.py
test/test_mercury_report.py
test/test_mercury_result.py
test/test_mercury_retrieve_factor_content_request.py
test/test_o_auth_request.py
test/test_o_auth_response.py
