Metadata-Version: 1.0
Name: python-pymetrics-assessment-client
Version: 2.0.0
Summary: pymetrics Assessment API
Home-page: UNKNOWN
Author: OpenAPI Generator community
Author-email: team@openapitools.org
License: UNKNOWN
Keywords: OpenAPI,OpenAPI-Generator,pymetrics Assessment API
Platform: UNKNOWN
